easy_spider_tool_document/__init__.py
easy_spider_tool_document/data.py
easy_spider_tool_document/xpath.py
easy_spider_tool_document-1.0.13.dist-info/LICENSE
easy_spider_tool_document-1.0.13.dist-info/METADATA
easy_spider_tool_document-1.0.13.dist-info/WHEEL
easy_spider_tool_document-1.0.13.dist-info/top_level.txt
easy_spider_tool_document-1.0.13.dist-info/RECORD
