Metadata-Version: 2.1
Name: easy-spider-tool-document
Version: 1.0.13
Summary: easy-spider-tool 可选xpath/jsonpath聚合解析扩展包
Home-page: https://easy-spider-tool-document.xink.top/
Author: hanxinkong
Author-email: xinkonghan@gmail.com
License: MIT
Keywords: easy,spider,tool,document
Platform: UNKNOWN
Requires-Python: >=3.6.8
Requires-Dist: lxml (~=4.9.3)
